<?xml version="1.0" encoding="utf-8"?><toc><breadcrumbs><li><a href="cf45297b-d6e3-1cb1-ce38-aab28582c7b4.htm">Docs</a></li><li><a href="259acfed-53d2-1279-cefe-9b168dde20d7.htm">FSEngine.<wbr />Cell<wbr />System.<wbr />Effects.<wbr />Particles</a></li><li><a href="9445fbd5-ad93-c651-aa17-f233f48e7b76.htm">Particle<wbr />Engine</a></li></breadcrumbs><tocItems><li><a id="b65fa3c5-377b-0502-a706-9cfe3fb2d58a" href="b65fa3c5-377b-0502-a706-9cfe3fb2d58a.htm">Constructor</a></li><li><a id="0be1c5d3-682e-5ffd-8d54-c0de3a20e7dd" class="has-submenu" href="0be1c5d3-682e-5ffd-8d54-c0de3a20e7dd.htm"><span data-tocFile="../toc/IDBCE.xml" class="icon toggle" onclick="ToggleExpandCollapse(this); return false;"><i class="fa fa-angle-right"> </i></span>Methods</a><ul class="toc-menu is-hidden"> </ul></li><li><a id="02e75fbb-c979-004b-2e8d-9f1a5f91be7d" class="has-submenu" href="02e75fbb-c979-004b-2e8d-9f1a5f91be7d.htm"><span data-tocFile="../toc/IDCCE.xml" class="icon toggle" onclick="ToggleExpandCollapse(this); return false;"><i class="fa fa-angle-right"> </i></span>Fields</a><ul class="toc-menu is-hidden"> </ul></li></tocItems></toc>